huaweicloudsdkdris/__init__.py
huaweicloudsdkdris/v1/__init__.py
huaweicloudsdkdris/v1/dris_async_client.py
huaweicloudsdkdris/v1/dris_client.py
huaweicloudsdkdris/v1/model/__init__.py
huaweicloudsdkdris/v1/model/add_forwarding_config_request_dto.py
huaweicloudsdkdris/v1/model/add_forwarding_configs_request.py
huaweicloudsdkdris/v1/model/add_forwarding_configs_response.py
huaweicloudsdkdris/v1/model/add_rsu_dto.py
huaweicloudsdkdris/v1/model/add_rsu_model.py
huaweicloudsdkdris/v1/model/add_traffic_controller_dto.py
huaweicloudsdkdris/v1/model/add_traffic_event_dto.py
huaweicloudsdkdris/v1/model/add_v2_x_edge_app_dto.py
huaweicloudsdkdris/v1/model/add_v2_x_edge_data_channel_dto.py
huaweicloudsdkdris/v1/model/add_v2_x_edge_dto.py
huaweicloudsdkdris/v1/model/add_vehicle_dto.py
huaweicloudsdkdris/v1/model/batch_show_edge_app_versions_request.py
huaweicloudsdkdris/v1/model/batch_show_edge_app_versions_response.py
huaweicloudsdkdris/v1/model/batch_show_edge_apps_request.py
huaweicloudsdkdris/v1/model/batch_show_edge_apps_response.py
huaweicloudsdkdris/v1/model/batch_show_ipcs_request.py
huaweicloudsdkdris/v1/model/batch_show_ipcs_response.py
huaweicloudsdkdris/v1/model/batch_show_radars_request.py
huaweicloudsdkdris/v1/model/batch_show_radars_response.py
huaweicloudsdkdris/v1/model/batch_show_rsus_request.py
huaweicloudsdkdris/v1/model/batch_show_rsus_response.py
huaweicloudsdkdris/v1/model/batch_show_traffic_controllers_request.py
huaweicloudsdkdris/v1/model/batch_show_traffic_controllers_response.py
huaweicloudsdkdris/v1/model/batch_show_traffic_events_request.py
huaweicloudsdkdris/v1/model/batch_show_traffic_events_response.py
huaweicloudsdkdris/v1/model/batch_show_vehicles_request.py
huaweicloudsdkdris/v1/model/batch_show_vehicles_response.py
huaweicloudsdkdris/v1/model/channel.py
huaweicloudsdkdris/v1/model/congestion_info.py
huaweicloudsdkdris/v1/model/congestion_lanes_info.py
huaweicloudsdkdris/v1/model/container_configs_dto.py
huaweicloudsdkdris-3.1.184.dist-info/METADATA
huaweicloudsdkdris-3.1.184.dist-info/WHEEL
huaweicloudsdkdris-3.1.184.dist-info/licenses/LICENSE
huaweicloudsdkdris-3.1.184.dist-info/RECORD
